msbench_analysis_mcp/__init__.py
msbench_analysis_mcp/__main__.py
msbench_analysis_mcp/analysis_server.py
msbench_analysis_mcp/cls_log_analysis.py
msbench_analysis_mcp/trajectory_log_analysis.py
msbench_analysis_mcp/utils.py
msbench_analysis_mcp-0.2.1.dist-info/METADATA
msbench_analysis_mcp-0.2.1.dist-info/WHEEL
msbench_analysis_mcp-0.2.1.dist-info/entry_points.txt
msbench_analysis_mcp-0.2.1.dist-info/RECORD
