Metadata-Version: 2.4
Name: msbench-analysis-mcp
Version: 0.2.1
Summary: This tool is designed to analyze MSBench log zip file, automatically extract error information from nested logs.
Requires-Python: >=3.10
Requires-Dist: mcp[cli]>=1.9.4
Requires-Dist: openpyxl>=3.1.5
Requires-Dist: pandas>=2.3.0
Requires-Dist: tabulate>=0.9.0
